twoprocessmodel/__init__.py
twoprocessmodel/circadianProcess.py
twoprocessmodel/homeostaticProcess.py
twoprocessmodel/noiseProcess.py
twoprocessmodel-0.0.1.dist-info/DESCRIPTION.rst
twoprocessmodel-0.0.1.dist-info/METADATA
twoprocessmodel-0.0.1.dist-info/RECORD
twoprocessmodel-0.0.1.dist-info/WHEEL
twoprocessmodel-0.0.1.dist-info/metadata.json
twoprocessmodel-0.0.1.dist-info/top_level.txt
